kkpyui/.git/.DS_Store
kkpyui/.git/COMMIT_EDITMSG
kkpyui/.git/FETCH_HEAD
kkpyui/.git/HEAD
kkpyui/.git/ORIG_HEAD
kkpyui/.git/config
kkpyui/.git/description
kkpyui/.git/hooks/applypatch-msg.sample
kkpyui/.git/hooks/commit-msg.sample
kkpyui/.git/hooks/fsmonitor-watchman.sample
kkpyui/.git/hooks/post-checkout
kkpyui/.git/hooks/post-commit
kkpyui/.git/hooks/post-merge
kkpyui/.git/hooks/post-update.sample
kkpyui/.git/hooks/pre-applypatch.sample
kkpyui/.git/hooks/pre-commit.sample
kkpyui/.git/hooks/pre-merge-commit.sample
kkpyui/.git/hooks/pre-push
kkpyui/.git/hooks/pre-push.sample
kkpyui/.git/hooks/pre-rebase.sample
kkpyui/.git/hooks/pre-receive.sample
kkpyui/.git/hooks/prepare-commit-msg.sample
kkpyui/.git/hooks/push-to-checkout.sample
kkpyui/.git/hooks/sendemail-validate.sample
kkpyui/.git/hooks/update.sample
kkpyui/.git/index
kkpyui/.git/info/exclude
kkpyui/.git/lfs/cache/locks/refs/heads/master/verifiable
kkpyui/.git/lfs/objects/53/6e/536e86a44a1393357fd4d4702ed32e632f18ca133e46d77eb41a8c7662242ab2
kkpyui/.git/logs/HEAD
kkpyui/.git/logs/refs/heads/master
kkpyui/.git/logs/refs/remotes/origin/HEAD
kkpyui/.git/logs/refs/remotes/origin/master
kkpyui/.git/objects/00/84e5e4ebdaef1e407a3aab7a9f294370fafe58
kkpyui/.git/objects/01/3c2a712d4689238253ee76ce606a830aa23fe7
kkpyui/.git/objects/01/41645540f5624b1300088b4ad63feffe86176d
kkpyui/.git/objects/01/484f9798f968c44ecba500b6a1ec13bb7e249f
kkpyui/.git/objects/01/7ca7545a04d091729d640c3d8e04116d358528
kkpyui/.git/objects/01/8026275a2aa097689ce151d8d77804201e016a
kkpyui/.git/objects/01/95b0404c1baf1c2af9d1a0d42aec0b87d7d76a
kkpyui/.git/objects/01/a8bdd3583f8a229e6d13759a5dcc66aab0f2f9
kkpyui/.git/objects/01/b082a0d89df8403a33375426f3e7e5e37043e2
kkpyui/.git/objects/01/c8c62455517760c127326cb5a958e73f1f8fd3
kkpyui/.git/objects/01/ece02b7da639eba89956a2935003e85bdfe255
kkpyui/.git/objects/02/c64e6ab78646c3612fe6e52e4e08f71b90278f
kkpyui/.git/objects/03/08ba466f839176d8e56c54bbe55c6e61315aac
kkpyui-0.33.0.dist-info/LICENSE
kkpyui-0.33.0.dist-info/METADATA
kkpyui-0.33.0.dist-info/WHEEL
kkpyui-0.33.0.dist-info/RECORD
