Metadata-Version: 2.1
Name: kkpyui
Version: 0.33.0
Summary: Tkinter-based GUI widget library for small tools
Author: Beinan Li
Author-email: li.beinan@gmail.com
Requires-Python: >=3.11,<4.0
Classifier: Programming Language :: Python :: 3
Classifier: Programming Language :: Python :: 3.11
Requires-Dist: kkpyutil
